crewmate/__init__.py
crewmate/cost_functions.py
crewmate/fit.py
crewmate/qctrl.py
crewmate/utils.py
crewmate-0.0.0.7.dist-info/METADATA
crewmate-0.0.0.7.dist-info/WHEEL
crewmate-0.0.0.7.dist-info/top_level.txt
crewmate-0.0.0.7.dist-info/RECORD
