Metadata-Version: 2.1
Name: crewmate
Version: 0.0.0.7
Home-page: https://github.com/Qcrew/crewmate
Author: Qcrew
Author-email: general.qcrew@gmail.com
Requires-Dist: numpy
Provides-Extra: dev
Requires-Dist: pytest (>=3.7) ; extra == 'dev'
Requires-Dist: check-manifest (>=0.49) ; extra == 'dev'
